{
  "requestId": "cache-1772293389664-86720",
  "selectedUrls": [
    "https://gsa.gov/"
  ],
  "requestedCount": 100,
  "returnedCount": 1,
  "randomShareCount": 0,
  "shortfallCount": 99,
  "priorityCoverage": {
    "homepage": true,
    "search": false,
    "accessibility": false,
    "topTask": false,
    "contact": false,
    "about": false,
    "help": false,
    "resources": false
  },
  "languageDistribution": {
    "primary": 1,
    "additional": 0
  },
  "totalDiscoveredPages": 1,
  "discoverySummary": {
    "requestId": "cache-1772293389664-86720",
    "sourcesAttempted": [
      "sitemap",
      "homepage-fallback"
    ],
    "fallbackUsed": true,
    "fallbackTriggerReasons": [
      "shortfall-or-priority-gap"
    ],
    "cacheHit": false,
    "cacheCleared": false,
    "warnings": [
      "Sitemap fetch unavailable for https://gsa.gov/sitemap.xml",
      "Homepage fallback unavailable."
    ],
    "sourceCounts": {
      "raw": {
        "sitemap": 0,
        "homepage-fallback": 0
      },
      "accepted": {
        "critical-pages": 1
      }
    },
    "priorityCoverage": {
      "homepage": true,
      "search": false,
      "accessibility": false,
      "topTask": false,
      "contact": false,
      "about": false,
      "help": false,
      "resources": false
    },
    "scoreDiagnostics": {}
  },
  "generatedAt": "2026-02-28T15:43:09.711Z",
  "generatedBy": "github-action-cache"
}